django_whiff/__init__.py
django_whiff/apps.py
django_whiff/templatetags/__init__.py
django_whiff/templatetags/whiff.py
django_whiff-0.1.1.dist-info/METADATA
django_whiff-0.1.1.dist-info/WHEEL
django_whiff-0.1.1.dist-info/licenses/LICENSE
django_whiff-0.1.1.dist-info/RECORD
